setup.py
xdspider/__init__.py
xdspider/xdspider.py
xdspider.egg-info/PKG-INFO
xdspider.egg-info/SOURCES.txt
xdspider.egg-info/dependency_links.txt
xdspider.egg-info/not-zip-safe
xdspider.egg-info/top_level.txt