Metadata-Version: 1.0
Name: xdspider
Version: 0.2
Summary: Python Web Spider
Home-page: https://github.com/xX-MLG-Xx/xdspider
Author: Dean Van Greunen
Author-email: deanvg9000@gmail.com
License: GPL v3
Platform: UNKNOWN
